{
  "name": "Нуль-Пустота",
  "intro": "🌑 *Внимание!* Из тени выполз **Нуль-Пустота**! Он хочет стереть все числа!",
  "victory": "✨ Ты победила Нуль-Пустоту! Числа снова светятся!",
  "reward": "звезда_сложения",
  "tasks": [
    {
      "question": "Сколько будет 27 + 18?",
      "answer": 45,
      "hint": "Двадцать семь плюс восемнадцать"
    },
    {
      "question": "У Морковки 35 морковок. Ей дали ещё 29. Сколько стало?",
      "answer": 64,
      "hint": "35 + 29"
    },
    {
      "question": "В саду росло 42 цветка. Посадили ещё 33. Сколько теперь?",
      "answer": 75,
      "hint": "42 + 33"
    },
    {
      "question": "Морковка собрала 51 морковку утром и 28 вечером. Сколько всего?",
      "answer": 79,
      "hint": "51 + 28"
    },
    {
      "question": "Сколько углов у квадрата?",
      "answer": 4,
      "hint": "Квадрат — честная фигура!"
    },
    {
      "question": "Сколько будет 39 + 24?",
      "answer": 63,
      "hint": "Тридцать девять плюс двадцать четыре"
    },
    {
      "question": "У Георгия 47 слизней. Он нашёл ещё 26. Сколько у него слизней?",
      "answer": 73,
      "hint": "47 + 26"
    },
    {
      "question": "На поляне 53 бабочки. Прилетели ещё 29. Сколько бабочек?",
      "answer": 82,
      "hint": "53 + 29"
    },
    {
      "question": "Морковка прочитала 64 страницы утром и 27 вечером. Сколько всего?",
      "answer": 91,
      "hint": "64 + 27"
    },
    {
      "question": "Сколько сторон у треугольника?",
      "answer": 3,
      "hint": "Три стороны — три угла!"
    },
    {
      "question": "Сколько будет 48 + 35?",
      "answer": 83,
      "hint": "Сорок восемь плюс тридцать пять"
    },
    {
      "question": "В корзине 59 яблок. Добавили ещё 24. Сколько яблок?",
      "answer": 83,
      "hint": "59 + 24"
    },
    {
      "question": "У Манюни 67 звёзд. Она получила ещё 25. Сколько звёзд?",
      "answer": 92,
      "hint": "67 + 25"
    },
    {
      "question": "Сколько пальцев на одной руке?",
      "answer": 5,
      "hint": "Один, два, три, четыре, пять!"
    },
    {
      "question": "Сколько будет 56 + 27?",
      "answer": 83,
      "hint": "Пятьдесят шесть плюс двадцать семь"
    },
    {
      "question": "У Морковки 68 морковок. Ей дали ещё 19. Сколько стало?",
      "answer": 87,
      "hint": "68 + 19"
    },
    {
      "question": "В саду росло 74 цветка. Посадили ещё 18. Сколько теперь?",
      "answer": 92,
      "hint": "74 + 18"
    },
    {
      "question": "Сколько колёс у велосипеда?",
      "answer": 2,
      "hint": "Два колеса — и вперёд!"
    },
    {
      "question": "Сколько будет 63 + 28?",
      "answer": 91,
      "hint": "Шестьдесят три плюс двадцать восемь"
    },
    {
      "question": "Морковка собрала 75 морковок утром и 17 вечером. Сколько всего?",
      "answer": 92,
      "hint": "75 + 17"
    },
    {
      "question": "Сколько глаз у человека?",
      "answer": 2,
      "hint": "Левый и правый!"
    },
    {
      "question": "Сколько будет 72 + 19?",
      "answer": 91,
      "hint": "Семьдесят два плюс девятнадцать"
    },
    {
      "question": "У Георгия 83 слизня. Он нашёл ещё 18. Сколько у него слизней?",
      "answer": 101,
      "hint": "83 + 18"
    },
    {
      "question": "На дереве 85 птиц. Прилетели ещё 16. Сколько птиц?",
      "answer": 101,
      "hint": "85 + 16"
    },
    {
      "question": "Сколько носов у человека?",
      "answer": 1,
      "hint": "Один нос — и всё!"
    },
    {
      "question": "Сколько будет 84 + 17?",
      "answer": 101,
      "hint": "Восемьдесят четыре плюс семнадцать"
    },
    {
      "question": "В корзине 92 яблока. Добавили ещё 9. Сколько яблок?",
      "answer": 101,
      "hint": "92 + 9"
    },
    {
      "question": "Сколько ушей у зайца?",
      "answer": 2,
      "hint": "Два длинных уха!"
    },
    {
      "question": "Сколько будет 93 + 8?",
      "answer": 101,
      "hint": "Девяносто три плюс восемь"
    },
    {
      "question": "У Манюни 95 звёзд. Она получила ещё 6. Сколько звёзд?",
      "answer": 101,
      "hint": "95 + 6"
    }
  ]
}